<annotation>
	<folder>re_img</folder>
	<filename>109.DSP0044818-preview-logo-watermarked.jpg</filename>
	
	<source>
		<database>Unknown</database>
	</source>
	<size>
		<width>533</width>
		<height>800</height>
		<depth>3</depth>
	</size>
	<segmented>0</segmented>
	<object>
		<name>smile</name>
		<pose>Unspecified</pose>
		<truncated>0</truncated>
		<difficult>0</difficult>
		<bndbox>
			<xmin>135</xmin>
			<ymin>152</ymin>
			<xmax>367</xmax>
			<ymax>448</ymax>
		</bndbox>
	</object>
</annotation>