<annotation>
	<folder>re_img (3)</folder>
	<filename>299.1kbv6l.jpg</filename>
	
	<source>
		<database>Unknown</database>
	</source>
	<size>
		<width>620</width>
		<height>412</height>
		<depth>3</depth>
	</size>
	<segmented>0</segmented>
	<object>
		<name>smile</name>
		<pose>Unspecified</pose>
		<truncated>0</truncated>
		<difficult>0</difficult>
		<bndbox>
			<xmin>151</xmin>
			<ymin>132</ymin>
			<xmax>276</xmax>
			<ymax>274</ymax>
		</bndbox>
	</object>
</annotation>