<annotation>
	<folder>anger</folder>
	<filename>beautiful-asian-mother-scolding-her-260nw-671747422.jpg</filename>
	
	<source>
		<database>Unknown</database>
	</source>
	<size>
		<width>390</width>
		<height>280</height>
		<depth>3</depth>
	</size>
	<segmented>0</segmented>
	<object>
		<name>anger</name>
		<pose>Unspecified</pose>
		<truncated>0</truncated>
		<difficult>0</difficult>
		<bndbox>
			<xmin>274</xmin>
			<ymin>120</ymin>
			<xmax>314</xmax>
			<ymax>166</ymax>
		</bndbox>
	</object>
</annotation>