<annotation>
	<folder>surprise</folder>
	<filename>wow-surprised-face-asian-man-260nw-1356497306.jpg</filename>
	
	<source>
		<database>Unknown</database>
	</source>
	<size>
		<width>390</width>
		<height>280</height>
		<depth>3</depth>
	</size>
	<segmented>0</segmented>
	<object>
		<name>surprise</name>
		<pose>Unspecified</pose>
		<truncated>0</truncated>
		<difficult>0</difficult>
		<bndbox>
			<xmin>224</xmin>
			<ymin>67</ymin>
			<xmax>287</xmax>
			<ymax>173</ymax>
		</bndbox>
	</object>
</annotation>